parametrize_from_file/__init__.py
parametrize_from_file/errors.py
parametrize_from_file/loaders.py
parametrize_from_file/namespace.py
parametrize_from_file/parameters.py
parametrize_from_file/schema.py
parametrize_from_file/utils.py
parametrize_from_file-0.19.0.dist-info/WHEEL
parametrize_from_file-0.19.0.dist-info/METADATA
parametrize_from_file-0.19.0.dist-info/RECORD
