Metadata-Version: 2.1
Name: parametrize_from_file
Version: 0.19.0
Summary: Parametrize test functions with values read from config files.
Author-email: Kale Kundert <kale@thekunderts.net>
Requires-Python: ~=3.7
Classifier: Programming Language :: Python :: 3
Classifier: License :: OSI Approved :: MIT License
Requires-Dist: toml
Requires-Dist: pyyaml
Requires-Dist: nestedtext
Requires-Dist: tidyexc
Requires-Dist: pytest
Requires-Dist: more_itertools~=8.10
Requires-Dist: decopatch
Requires-Dist: sphinx ; extra == "doc"
Requires-Dist: sphinx_rtd_theme ; extra == "doc"
Requires-Dist: autoclasstoc ; extra == "doc"
Requires-Dist: sphinx-toolbox ; extra == "doc"
Requires-Dist: pytest ; extra == "test"
Requires-Dist: pytest-cov ; extra == "test"
Requires-Dist: pytest_tmp_files ; extra == "test"
Requires-Dist: coveralls ; extra == "test"
Requires-Dist: numpy ; extra == "test"
Project-URL: Bug Tracker, https://github.com/kalekundert/parametrize_from_file/issues
Project-URL: Continuous Integration, https://github.com/kalekundert/parametrize_from_file/actions
Project-URL: Documentation, https://parametrize-from-file.readthedocs.io/en/latest/
Project-URL: Test Coverage, https://coveralls.io/github/kalekundert/parametrize_from_file
Project-URL: Version Control, https://github.com/kalekundert/parametrize_from_file
Provides-Extra: doc
Provides-Extra: test
